circe/metrics.py
circe/inverse_covariance.py
circe/metacells.py
circe/rank_correlation.py
circe/__init__.py
circe/pyquic.cpython-312-darwin.so
circe/downloads.py
circe/utils.py
circe/ccan_module.py
circe/quic_graph_lasso.py
circe/draw.py
circe/circe.py
circe_py-0.3.9.dist-info/RECORD
circe_py-0.3.9.dist-info/WHEEL
circe_py-0.3.9.dist-info/top_level.txt
circe_py-0.3.9.dist-info/METADATA
circe_py-0.3.9.dist-info/licenses/LICENSE.txt
