Metadata-Version: 2.4
Name: circe-py
Version: 0.3.9
Summary: Circe: Package for building co-accessibility networks from ATAC-seq data.
Home-page: https://github.com/cantinilab/circe
Author: Remi-Trimbour
Author-email: remi.trimbour@pasteur.fr
Maintainer: Remi-Trimbour
Maintainer-email: remi.trimbour@gmail.com
License: GPL-3.0-only
Requires-Python: >=3.8,<4.0
License-File: LICENSE.txt
Requires-Dist: Cython
Requires-Dist: numpy<2.0.0
Requires-Dist: pandas
Requires-Dist: scikit-learn>=1.6
Requires-Dist: joblib>=1.1.0
Requires-Dist: scanpy>=1.8.1
Requires-Dist: anndata
Requires-Dist: rich>=10.12.0
Requires-Dist: dask
Requires-Dist: distributed
Requires-Dist: attrs>=20.3; python_version < "3.12"
Requires-Dist: attrs>=23.2; python_version >= "3.12"
Provides-Extra: downloads
Requires-Dist: pybiomart; extra == "downloads"
Dynamic: author
Dynamic: author-email
Dynamic: description
Dynamic: description-content-type
Dynamic: home-page
Dynamic: license
Dynamic: license-file
Dynamic: maintainer
Dynamic: maintainer-email
Dynamic: provides-extra
Dynamic: requires-dist
Dynamic: requires-python
Dynamic: summary
